llsd_asgi/__init__.py
llsd_asgi/middleware.py
llsd_asgi-0.2.2.dist-info/LICENSE
llsd_asgi-0.2.2.dist-info/METADATA
llsd_asgi-0.2.2.dist-info/WHEEL
llsd_asgi-0.2.2.dist-info/top_level.txt
llsd_asgi-0.2.2.dist-info/RECORD
