Metadata-Version: 2.1
Name: llsd-asgi
Version: 0.2.2
Author-email: Bennett Goble <151138+bennettgoble@users.noreply.github.com>
License: MIT
Project-URL: Homepage, https://github.com/secondlife/llsd-asgi
Classifier: Intended Audience :: Developers
Classifier: License :: OSI Approved :: MIT License
Classifier: Operating System :: OS Independent
Classifier: Programming Language :: Python :: 3
License-File: LICENSE
Requires-Dist: llsd
Requires-Dist: starlette
Provides-Extra: dev
Requires-Dist: pytest >6 ; extra == 'dev'
Requires-Dist: pytest-cov ; extra == 'dev'
Requires-Dist: pytest-asyncio ; extra == 'dev'
Requires-Dist: httpx ; extra == 'dev'
